Metadata-Version: 2.1
Name: evdetect
Version: 0.2.0
Summary: Parametric event detection & inference library
Home-page: https://github.com/nikosga/evDetect/tree/main
Author: Nick Gavriil
License: Apache-2.0
License-File: LICENSE.txt
Requires-Dist: pandas
Requires-Dist: numpy
Requires-Dist: statsmodels
Requires-Dist: matplotlib
Requires-Dist: seaborn
Requires-Dist: joblib
